<?xml version="1.0" encoding="UTF-8" ?>
<OpenSimDocument Version="40500">
	<ControlSet name="Control Set">
		<objects>
			<ControlLinear name="sternoclavicular_r2_reserve">
				<is_model_control>true</is_model_control>
				<extrapolate>true</extrapolate>
				<default_min>0.02</default_min>
				<default_max>1</default_max>
				<filter_on>false</filter_on>
				<use_steps>false</use_steps>
				<x_nodes>
					<ControlLinearNode>
						<t>0</t>
						<value>-0.045533985547970487</value>
					</ControlLinearNode>
					<ControlLinearNode>
						<t>0.01</t>
						<value>-0.04553398554794217</value>
					</ControlLinearNode>
				</x_nodes>
				<min_nodes />
				<max_nodes />
				<kp>100</kp>
				<kv>20</kv>
			</ControlLinear>
			<ControlLinear name="sternoclavicular_r3_reserve">
				<is_model_control>true</is_model_control>
				<extrapolate>true</extrapolate>
				<default_min>0.02</default_min>
				<default_max>1</default_max>
				<filter_on>false</filter_on>
				<use_steps>false</use_steps>
				<x_nodes>
					<ControlLinearNode>
						<t>0</t>
						<value>0.019286047191102374</value>
					</ControlLinearNode>
					<ControlLinearNode>
						<t>0.01</t>
						<value>0.01928604719109011</value>
					</ControlLinearNode>
				</x_nodes>
				<min_nodes />
				<max_nodes />
				<kp>100</kp>
				<kv>20</kv>
			</ControlLinear>
			<ControlLinear name="unrotscap_r3_reserve">
				<is_model_control>true</is_model_control>
				<extrapolate>true</extrapolate>
				<default_min>0.02</default_min>
				<default_max>1</default_max>
				<filter_on>false</filter_on>
				<use_steps>false</use_steps>
				<x_nodes>
					<ControlLinearNode>
						<t>0</t>
						<value>-0.019286047191093246</value>
					</ControlLinearNode>
					<ControlLinearNode>
						<t>0.01</t>
						<value>-0.019286047191081575</value>
					</ControlLinearNode>
				</x_nodes>
				<min_nodes />
				<max_nodes />
				<kp>100</kp>
				<kv>20</kv>
			</ControlLinear>
			<ControlLinear name="unrotscap_r2_reserve">
				<is_model_control>true</is_model_control>
				<extrapolate>true</extrapolate>
				<default_min>0.02</default_min>
				<default_max>1</default_max>
				<filter_on>false</filter_on>
				<use_steps>false</use_steps>
				<x_nodes>
					<ControlLinearNode>
						<t>0</t>
						<value>0.045533985547949699</value>
					</ControlLinearNode>
					<ControlLinearNode>
						<t>0.01</t>
						<value>0.045533985547919653</value>
					</ControlLinearNode>
				</x_nodes>
				<min_nodes />
				<max_nodes />
				<kp>100</kp>
				<kv>20</kv>
			</ControlLinear>
			<ControlLinear name="acromioclavicular_r2_reserve">
				<is_model_control>true</is_model_control>
				<extrapolate>true</extrapolate>
				<default_min>0.02</default_min>
				<default_max>1</default_max>
				<filter_on>false</filter_on>
				<use_steps>false</use_steps>
				<x_nodes>
					<ControlLinearNode>
						<t>0</t>
						<value>-0.0092197058409418456</value>
					</ControlLinearNode>
					<ControlLinearNode>
						<t>0.01</t>
						<value>-0.0092197058409350472</value>
					</ControlLinearNode>
				</x_nodes>
				<min_nodes />
				<max_nodes />
				<kp>100</kp>
				<kv>20</kv>
			</ControlLinear>
			<ControlLinear name="acromioclavicular_r3_reserve">
				<is_model_control>true</is_model_control>
				<extrapolate>true</extrapolate>
				<default_min>0.02</default_min>
				<default_max>1</default_max>
				<filter_on>false</filter_on>
				<use_steps>false</use_steps>
				<x_nodes>
					<ControlLinearNode>
						<t>0</t>
						<value>0.07451041951705184</value>
					</ControlLinearNode>
					<ControlLinearNode>
						<t>0.01</t>
						<value>0.074510419517000284</value>
					</ControlLinearNode>
				</x_nodes>
				<min_nodes />
				<max_nodes />
				<kp>100</kp>
				<kv>20</kv>
			</ControlLinear>
			<ControlLinear name="acromioclavicular_r1_reserve">
				<is_model_control>true</is_model_control>
				<extrapolate>true</extrapolate>
				<default_min>0.02</default_min>
				<default_max>1</default_max>
				<filter_on>false</filter_on>
				<use_steps>false</use_steps>
				<x_nodes>
					<ControlLinearNode>
						<t>0</t>
						<value>0.033491920776072971</value>
					</ControlLinearNode>
					<ControlLinearNode>
						<t>0.01</t>
						<value>0.033491920776046277</value>
					</ControlLinearNode>
				</x_nodes>
				<min_nodes />
				<max_nodes />
				<kp>100</kp>
				<kv>20</kv>
			</ControlLinear>
			<ControlLinear name="unrothum_r1_reserve">
				<is_model_control>true</is_model_control>
				<extrapolate>true</extrapolate>
				<default_min>0.02</default_min>
				<default_max>1</default_max>
				<filter_on>false</filter_on>
				<use_steps>false</use_steps>
				<x_nodes>
					<ControlLinearNode>
						<t>0</t>
						<value>-0.033491920776067191</value>
					</ControlLinearNode>
					<ControlLinearNode>
						<t>0.01</t>
						<value>-0.033491920776044223</value>
					</ControlLinearNode>
				</x_nodes>
				<min_nodes />
				<max_nodes />
				<kp>100</kp>
				<kv>20</kv>
			</ControlLinear>
			<ControlLinear name="unrothum_r3_reserve">
				<is_model_control>true</is_model_control>
				<extrapolate>true</extrapolate>
				<default_min>0.02</default_min>
				<default_max>1</default_max>
				<filter_on>false</filter_on>
				<use_steps>false</use_steps>
				<x_nodes>
					<ControlLinearNode>
						<t>0</t>
						<value>-0.074510419517064885</value>
					</ControlLinearNode>
					<ControlLinearNode>
						<t>0.01</t>
						<value>-0.074510419517012816</value>
					</ControlLinearNode>
				</x_nodes>
				<min_nodes />
				<max_nodes />
				<kp>100</kp>
				<kv>20</kv>
			</ControlLinear>
			<ControlLinear name="unrothum_r2_reserve">
				<is_model_control>true</is_model_control>
				<extrapolate>true</extrapolate>
				<default_min>0.02</default_min>
				<default_max>1</default_max>
				<filter_on>false</filter_on>
				<use_steps>false</use_steps>
				<x_nodes>
					<ControlLinearNode>
						<t>0</t>
						<value>0.0092197058409379581</value>
					</ControlLinearNode>
					<ControlLinearNode>
						<t>0.01</t>
						<value>0.0092197058409317391</value>
					</ControlLinearNode>
				</x_nodes>
				<min_nodes />
				<max_nodes />
				<kp>100</kp>
				<kv>20</kv>
			</ControlLinear>
			<ControlLinear name="elv_angle_reserve">
				<is_model_control>true</is_model_control>
				<extrapolate>true</extrapolate>
				<default_min>0.02</default_min>
				<default_max>1</default_max>
				<filter_on>false</filter_on>
				<use_steps>false</use_steps>
				<x_nodes>
					<ControlLinearNode>
						<t>0</t>
						<value>0.083664621931050676</value>
					</ControlLinearNode>
					<ControlLinearNode>
						<t>0.01</t>
						<value>0.083664621931290595</value>
					</ControlLinearNode>
				</x_nodes>
				<min_nodes />
				<max_nodes />
				<kp>100</kp>
				<kv>20</kv>
			</ControlLinear>
			<ControlLinear name="shoulder_elv_reserve">
				<is_model_control>true</is_model_control>
				<extrapolate>true</extrapolate>
				<default_min>0.02</default_min>
				<default_max>1</default_max>
				<filter_on>false</filter_on>
				<use_steps>false</use_steps>
				<x_nodes>
					<ControlLinearNode>
						<t>0</t>
						<value>0.18815654335408663</value>
					</ControlLinearNode>
					<ControlLinearNode>
						<t>0.01</t>
						<value>0.18815654335395632</value>
					</ControlLinearNode>
				</x_nodes>
				<min_nodes />
				<max_nodes />
				<kp>100</kp>
				<kv>20</kv>
			</ControlLinear>
			<ControlLinear name="shoulder1_r2_reserve">
				<is_model_control>true</is_model_control>
				<extrapolate>true</extrapolate>
				<default_min>0.02</default_min>
				<default_max>1</default_max>
				<filter_on>false</filter_on>
				<use_steps>false</use_steps>
				<x_nodes>
					<ControlLinearNode>
						<t>0</t>
						<value>-0.083664621931052952</value>
					</ControlLinearNode>
					<ControlLinearNode>
						<t>0.01</t>
						<value>-0.083664621931292718</value>
					</ControlLinearNode>
				</x_nodes>
				<min_nodes />
				<max_nodes />
				<kp>100</kp>
				<kv>20</kv>
			</ControlLinear>
			<ControlLinear name="shoulder_rot_reserve">
				<is_model_control>true</is_model_control>
				<extrapolate>true</extrapolate>
				<default_min>0.02</default_min>
				<default_max>1</default_max>
				<filter_on>false</filter_on>
				<use_steps>false</use_steps>
				<x_nodes>
					<ControlLinearNode>
						<t>0</t>
						<value>-0.16555466961204493</value>
					</ControlLinearNode>
					<ControlLinearNode>
						<t>0.01</t>
						<value>-0.1655546696120348</value>
					</ControlLinearNode>
				</x_nodes>
				<min_nodes />
				<max_nodes />
				<kp>100</kp>
				<kv>20</kv>
			</ControlLinear>
			<ControlLinear name="elbow_flexion_reserve">
				<is_model_control>true</is_model_control>
				<extrapolate>true</extrapolate>
				<default_min>0.02</default_min>
				<default_max>1</default_max>
				<filter_on>false</filter_on>
				<use_steps>false</use_steps>
				<x_nodes>
					<ControlLinearNode>
						<t>0</t>
						<value>0.28575296781574389</value>
					</ControlLinearNode>
					<ControlLinearNode>
						<t>0.01</t>
						<value>0.28575296781568582</value>
					</ControlLinearNode>
				</x_nodes>
				<min_nodes />
				<max_nodes />
				<kp>100</kp>
				<kv>20</kv>
			</ControlLinear>
			<ControlLinear name="pro_sup_reserve">
				<is_model_control>true</is_model_control>
				<extrapolate>true</extrapolate>
				<default_min>0.02</default_min>
				<default_max>1</default_max>
				<filter_on>false</filter_on>
				<use_steps>false</use_steps>
				<x_nodes>
					<ControlLinearNode>
						<t>0</t>
						<value>-0.013073036989613675</value>
					</ControlLinearNode>
					<ControlLinearNode>
						<t>0.01</t>
						<value>-0.013073036989611897</value>
					</ControlLinearNode>
				</x_nodes>
				<min_nodes />
				<max_nodes />
				<kp>100</kp>
				<kv>20</kv>
			</ControlLinear>
			<ControlLinear name="deviation_reserve">
				<is_model_control>true</is_model_control>
				<extrapolate>true</extrapolate>
				<default_min>0.02</default_min>
				<default_max>1</default_max>
				<filter_on>false</filter_on>
				<use_steps>false</use_steps>
				<x_nodes>
					<ControlLinearNode>
						<t>0</t>
						<value>-0.0087204741175162352</value>
					</ControlLinearNode>
					<ControlLinearNode>
						<t>0.01</t>
						<value>-0.008720474117550104</value>
					</ControlLinearNode>
				</x_nodes>
				<min_nodes />
				<max_nodes />
				<kp>100</kp>
				<kv>20</kv>
			</ControlLinear>
			<ControlLinear name="flexion_reserve">
				<is_model_control>true</is_model_control>
				<extrapolate>true</extrapolate>
				<default_min>0.02</default_min>
				<default_max>1</default_max>
				<filter_on>false</filter_on>
				<use_steps>false</use_steps>
				<x_nodes>
					<ControlLinearNode>
						<t>0</t>
						<value>-0.0086135490677654667</value>
					</ControlLinearNode>
					<ControlLinearNode>
						<t>0.01</t>
						<value>-0.0086135490677651493</value>
					</ControlLinearNode>
				</x_nodes>
				<min_nodes />
				<max_nodes />
				<kp>100</kp>
				<kv>20</kv>
			</ControlLinear>
			<ControlLinear name="wrist_hand_r1_reserve">
				<is_model_control>true</is_model_control>
				<extrapolate>true</extrapolate>
				<default_min>0.02</default_min>
				<default_max>1</default_max>
				<filter_on>false</filter_on>
				<use_steps>false</use_steps>
				<x_nodes>
					<ControlLinearNode>
						<t>0</t>
						<value>-0.011834910281865495</value>
					</ControlLinearNode>
					<ControlLinearNode>
						<t>0.01</t>
						<value>-0.011834910281836258</value>
					</ControlLinearNode>
				</x_nodes>
				<min_nodes />
				<max_nodes />
				<kp>100</kp>
				<kv>20</kv>
			</ControlLinear>
			<ControlLinear name="wrist_hand_r3_reserve">
				<is_model_control>true</is_model_control>
				<extrapolate>true</extrapolate>
				<default_min>0.02</default_min>
				<default_max>1</default_max>
				<filter_on>false</filter_on>
				<use_steps>false</use_steps>
				<x_nodes>
					<ControlLinearNode>
						<t>0</t>
						<value>-0.0043067745511911103</value>
					</ControlLinearNode>
					<ControlLinearNode>
						<t>0.01</t>
						<value>-0.0043067745511913957</value>
					</ControlLinearNode>
				</x_nodes>
				<min_nodes />
				<max_nodes />
				<kp>100</kp>
				<kv>20</kv>
			</ControlLinear>
		</objects>
		<groups />
	</ControlSet>
</OpenSimDocument>
